minesweeper_solver/__init__.py
minesweeper_solver/game.py
minesweeper_solver/generate_board.py
minesweeper_solver/solver.py
minesweeper_solver-0.1.4.dist-info/entry_points.txt
minesweeper_solver-0.1.4.dist-info/WHEEL
minesweeper_solver-0.1.4.dist-info/METADATA
minesweeper_solver-0.1.4.dist-info/RECORD
